{
        "name": "apm_energy_addon",
        "version": "0.19.50",
        "title": "Amator Phasma's Energy (Addon)",
        "author": "AmatorPhasma",
        "dependencies": [
                "base >= 0.18.26",
                "apm_resource_pack >= 0.19.02",
                "apm_lib >= 0.19.50",
                "? apm_power >= 0.19.50",
                "? apm_nuclear >= 0.19.50"
        ],
        "description": "This is a small mod that adds electric cars and tanks (thats needs batteries) and a charging station. Vanilla and Bob's batteries have now a fuel value, if these are depleted you can recharge them at a charging station.",
        "factorio_version": "1.1",
        "homepage": ""
}